{
  "id": "hero-tailwind-stats",
  "filename": "hero-tailwind-stats.tsx",
  "category": "hero",
  "style_tags": [
    "tailwind",
    "stats",
    "data-driven",
    "professional"
  ],
  "color_scheme": [
    "white",
    "gray"
  ],
  "complexity": "medium",
  "props_schema": {
    "title": "string",
    "description": "string",
    "stats": "array",
    "ctaButton": "object"
  },
  "dependencies": [],
  "description": "Tailwind CSS hero with statistics and metrics",
  "source": "Tailwind UI"
}